.bzrignore
setup.cfg
setup.py
docs/CREDITS.txt
docs/HISTORY.txt
docs/INSTALL.txt
docs/LICENSE.GPL
docs/LICENSE.txt
docs/README.txt
docs/TODO.txt
kss/__init__.py
kss.plugin.livesearch.egg-info/PKG-INFO
kss.plugin.livesearch.egg-info/SOURCES.txt
kss.plugin.livesearch.egg-info/dependency_links.txt
kss.plugin.livesearch.egg-info/entry_points.txt
kss.plugin.livesearch.egg-info/namespace_packages.txt
kss.plugin.livesearch.egg-info/requires.txt
kss.plugin.livesearch.egg-info/top_level.txt
kss/plugin/__init__.py
kss/plugin/livesearch/__init__.py
kss/plugin/livesearch/autocompleteview.pt
kss/plugin/livesearch/autocompleteview.py
kss/plugin/livesearch/config.py
kss/plugin/livesearch/configure.zcml
kss/plugin/livesearch/kss.plugin.livesearch-configure.zcml
kss/plugin/livesearch/livesearchview.py
kss/plugin/livesearch/version.txt
kss/plugin/livesearch/demo/__init__.py
kss/plugin/livesearch/demo/configure.zcml
kss/plugin/livesearch/demo/kss_livesearch_demo.css
kss/plugin/livesearch/demo/kss_livesearch_demo.kss
kss/plugin/livesearch/demo/kss_livesearch_demo.pt
kss/plugin/livesearch/demo/kss_livesearch_demo.py
kss/plugin/livesearch/demo/zopeconfig.py
kss/plugin/livesearch/demo/selenium_tests/README.txt
kss/plugin/livesearch/javascript/livesearch.js
kss/plugin/livesearch/tests/__init__.py