Metadata-Version: 1.0
Name: kss.plugin.livesearch
Version: 1.0dev-20080523
Summary: KSS livesearch / autocomplete plugin
Home-page: http://kssproject.org
Author: KissBooth collective
Author-email: UNKNOWN
License: UNKNOWN
Platform: UNKNOWN
